taurex_pymiescatt/__init__.py
taurex_pymiescatt/contributions/__init__.py
taurex_pymiescatt/contributions/pyleemie.py
taurex_pymiescatt/contributions/pymiescatt.py
taurex_pymiescatt/contributions/pymiescatt_aggregates.py
taurex_pymiescatt-1.0.2.dist-info/licenses/LICENSE
taurex_pymiescatt-1.0.2.dist-info/METADATA
taurex_pymiescatt-1.0.2.dist-info/WHEEL
taurex_pymiescatt-1.0.2.dist-info/entry_points.txt
taurex_pymiescatt-1.0.2.dist-info/top_level.txt
taurex_pymiescatt-1.0.2.dist-info/RECORD
