Metadata-Version: 2.4
Name: taurex_pymiescatt
Version: 1.0.2
Summary: Cloud retrieval capabilities for TauREx
Home-page: https://github.com/groningen-exoatmospheres/taurex-pymiescatt
Author: Quentin Changeat
Author-email: q.changeat@rug.nl
License: BSD
Requires: PyMieScatt
Provides: taurex_pymiescatt
License-File: LICENSE
Requires-Dist: taurex
Dynamic: author
Dynamic: author-email
Dynamic: home-page
Dynamic: license
Dynamic: license-file
Dynamic: provides
Dynamic: requires
Dynamic: requires-dist
Dynamic: summary
